codeseeker/__init__.py
codeseeker/__main__.py
codeseeker/base.py
codeseeker/seeker.py
codeseeker/utils.py
codeseeker/validators.py
codeseeker-0.0.9.dist-info/LICENSE
codeseeker-0.0.9.dist-info/METADATA
codeseeker-0.0.9.dist-info/WHEEL
codeseeker-0.0.9.dist-info/entry_points.txt
codeseeker-0.0.9.dist-info/top_level.txt
codeseeker-0.0.9.dist-info/RECORD
